{
  "kind": "collectionType",
  "collectionName": "ingredients",
  "info": {
    "singularName": "ingredient",
    "pluralName": "ingredients",
    "displayName": "Ingredient"
  },
  "options": {
    "draftAndPublish": true
  },
  "pluginOptions": {
    "i18n": {
      "localized": true
    }
  },
  "attributes": {
    "name": {
      "type": "string",
      "pluginOptions": {
        "i18n": {
          "localized": true
        }
      },
      "required": true,
      "unique": true
    },
    "description": {
      "type": "text",
      "pluginOptions": {
        "i18n": {
          "localized": true
        }
      }
    },
    "categories": {
      "type": "relation",
      "relation": "manyToMany",
      "target": "api::category.category",
      "mappedBy": "ingredients"
    }
  }
}
